pyttrex/__init__.py
pyttrex/api.py
pyttrex/currencies.py
pyttrex/markets.py
pyttrex-0.1.0.dist-info/WHEEL
pyttrex-0.1.0.dist-info/METADATA
pyttrex-0.1.0.dist-info/RECORD
