Metadata-Version: 2.1
Name: pyttrex
Version: 0.1.0
Summary: Bittrex python library
License: MIT
Author: Hakan Dilek
Author-email: hakandilek@gmail.com
Requires-Python: >=3.8,<4.0
Classifier: License :: OSI Approved :: MIT License
Classifier: Programming Language :: Python :: 3
Classifier: Programming Language :: Python :: 3.10
Classifier: Programming Language :: Python :: 3.8
Classifier: Programming Language :: Python :: 3.9
Requires-Dist: httpx (>=0.22.0,<0.23.0)
